{
  "aggiornato": "19/07/2026 17:32",
  "squadra_preferita": "KK THUNDER",
  "squadre": [
    "ALPI STARTER",
    "ARVALIA MARCONI",
    "ASD SFERA ROSSA",
    "ASD TECNO-SPORT ORSI",
    "ASD TECNO-SPORT PINGUINI",
    "BEAT",
    "CAM VOLLEY LIVE",
    "DOPOLAVORO ATAC-COTRAL",
    "KK 30TMCAP",
    "KK ASTRAVOLLEY",
    "KK FOREVER YOUNG",
    "KK LUPO ALBERTO",
    "KK MAXSTERCLASS",
    "KK PASTE",
    "KK THUNDER",
    "MULTIMEDIA MARCONI",
    "NEW PICCHE",
    "PINK PANTHERS DUEMILA12",
    "ROMA SPORTS",
    "SANTA MONICA",
    "SHARKS ASD",
    "TODOLOCO"
  ],
  "classifica": [
    {
      "posizione": 1,
      "squadra": "ASD TECNO-SPORT ORSI",
      "giocate": 6,
      "punteggio": 15,
      "set_vinti": 9,
      "set_persi": 9,
      "punti_fatti": 413,
      "punti_subiti": 409
    },
    {
      "posizione": 2,
      "squadra": "CAM VOLLEY LIVE",
      "giocate": 6,
      "punteggio": 14,
      "set_vinti": 9,
      "set_persi": 9,
      "punti_fatti": 422,
      "punti_subiti": 415
    },
    {
      "posizione": 3,
      "squadra": "ALPI STARTER",
      "giocate": 5,
      "punteggio": 12,
      "set_vinti": 8,
      "set_persi": 7,
      "punti_fatti": 380,
      "punti_subiti": 350
    },
    {
      "posizione": 4,
      "squadra": "ARVALIA MARCONI",
      "giocate": 6,
      "punteggio": 12,
      "set_vinti": 10,
      "set_persi": 8,
      "punti_fatti": 445,
      "punti_subiti": 429
    },
    {
      "posizione": 5,
      "squadra": "KK PASTE",
      "giocate": 6,
      "punteggio": 11,
      "set_vinti": 9,
      "set_persi": 9,
      "punti_fatti": 401,
      "punti_subiti": 417
    },
    {
      "posizione": 6,
      "squadra": "KK 30TMCAP",
      "giocate": 5,
      "punteggio": 10,
      "set_vinti": 10,
      "set_persi": 5,
      "punti_fatti": 367,
      "punti_subiti": 345
    },
    {
      "posizione": 7,
      "squadra": "ROMA SPORTS",
      "giocate": 5,
      "punteggio": 10,
      "set_vinti": 9,
      "set_persi": 6,
      "punti_fatti": 354,
      "punti_subiti": 318
    },
    {
      "posizione": 8,
      "squadra": "KK ASTRAVOLLEY",
      "giocate": 5,
      "punteggio": 10,
      "set_vinti": 6,
      "set_persi": 9,
      "punti_fatti": 321,
      "punti_subiti": 344
    },
    {
      "posizione": 9,
      "squadra": "TODOLOCO",
      "giocate": 6,
      "punteggio": 10,
      "set_vinti": 9,
      "set_persi": 9,
      "punti_fatti": 442,
      "punti_subiti": 433
    },
    {
      "posizione": 10,
      "squadra": "KK THUNDER",
      "giocate": 6,
      "punteggio": 10,
      "set_vinti": 9,
      "set_persi": 9,
      "punti_fatti": 434,
      "punti_subiti": 434
    },
    {
      "posizione": 11,
      "squadra": "PINK PANTHERS DUEMILA12",
      "giocate": 6,
      "punteggio": 10,
      "set_vinti": 9,
      "set_persi": 9,
      "punti_fatti": 429,
      "punti_subiti": 431
    },
    {
      "posizione": 12,
      "squadra": "KK MAXSTERCLASS",
      "giocate": 6,
      "punteggio": 10,
      "set_vinti": 9,
      "set_persi": 9,
      "punti_fatti": 423,
      "punti_subiti": 425
    },
    {
      "posizione": 13,
      "squadra": "BEAT",
      "giocate": 5,
      "punteggio": 9,
      "set_vinti": 8,
      "set_persi": 7,
      "punti_fatti": 357,
      "punti_subiti": 366
    },
    {
      "posizione": 14,
      "squadra": "KK FOREVER YOUNG",
      "giocate": 6,
      "punteggio": 9,
      "set_vinti": 10,
      "set_persi": 8,
      "punti_fatti": 432,
      "punti_subiti": 435
    },
    {
      "posizione": 15,
      "squadra": "ASD TECNO-SPORT PINGUINI",
      "giocate": 5,
      "punteggio": 8,
      "set_vinti": 7,
      "set_persi": 8,
      "punti_fatti": 339,
      "punti_subiti": 341
    },
    {
      "posizione": 16,
      "squadra": "NEW PICCHE",
      "giocate": 4,
      "punteggio": 7,
      "set_vinti": 7,
      "set_persi": 5,
      "punti_fatti": 270,
      "punti_subiti": 268
    },
    {
      "posizione": 17,
      "squadra": "DOPOLAVORO ATAC-COTRAL",
      "giocate": 6,
      "punteggio": 7,
      "set_vinti": 10,
      "set_persi": 8,
      "punti_fatti": 416,
      "punti_subiti": 418
    },
    {
      "posizione": 18,
      "squadra": "MULTIMEDIA MARCONI",
      "giocate": 6,
      "punteggio": 7,
      "set_vinti": 8,
      "set_persi": 10,
      "punti_fatti": 408,
      "punti_subiti": 400
    },
    {
      "posizione": 19,
      "squadra": "KK LUPO ALBERTO",
      "giocate": 6,
      "punteggio": 7,
      "set_vinti": 7,
      "set_persi": 11,
      "punti_fatti": 398,
      "punti_subiti": 417
    },
    {
      "posizione": 20,
      "squadra": "SANTA MONICA",
      "giocate": 4,
      "punteggio": 6,
      "set_vinti": 5,
      "set_persi": 7,
      "punti_fatti": 283,
      "punti_subiti": 294
    },
    {
      "posizione": 21,
      "squadra": "ASD SFERA ROSSA",
      "giocate": 5,
      "punteggio": 5,
      "set_vinti": 7,
      "set_persi": 8,
      "punti_fatti": 332,
      "punti_subiti": 337
    },
    {
      "posizione": 22,
      "squadra": "SHARKS ASD",
      "giocate": 5,
      "punteggio": 3,
      "set_vinti": 5,
      "set_persi": 10,
      "punti_fatti": 310,
      "punti_subiti": 350
    }
  ],
  "partite": [
    {
      "id": "111",
      "data": "01-04-2026 21:00:00",
      "casa": "CAM VOLLEY LIVE",
      "ospite": "DOPOLAVORO ATAC-COTRAL",
      "giocata": true,
      "risultato": "2-1",
      "set": [
        "25-18",
        "20-25",
        "25-22"
      ]
    },
    {
      "id": "112",
      "data": "31-03-2026 20:45:00",
      "casa": "KK PASTE",
      "ospite": "MULTIMEDIA MARCONI",
      "giocata": true,
      "risultato": "2-1",
      "set": [
        "25-16",
        "19-25",
        "28-26"
      ]
    },
    {
      "id": "113",
      "data": "31-03-2026 21:30:00",
      "casa": "KK FOREVER YOUNG",
      "ospite": "KK LUPO ALBERTO",
      "giocata": true,
      "risultato": "0-3",
      "set": [
        "18-25",
        "15-25",
        "19-25"
      ]
    },
    {
      "id": "114",
      "data": "01-04-2026 21:00:00",
      "casa": "PINK PANTHERS DUEMILA12",
      "ospite": "ASD TECNO-SPORT ORSI",
      "giocata": true,
      "risultato": "1-2",
      "set": [
        "22-25",
        "29-31",
        "25-19"
      ]
    },
    {
      "id": "115",
      "data": "31-03-2026 20:50:00",
      "casa": "TODOLOCO",
      "ospite": "ARVALIA MARCONI",
      "giocata": true,
      "risultato": "2-1",
      "set": [
        "25-17",
        "26-28",
        "29-27"
      ]
    },
    {
      "id": "116",
      "data": "01-04-2026 20:45:00",
      "casa": "KK THUNDER",
      "ospite": "KK MAXSTERCLASS",
      "giocata": true,
      "risultato": "0-3",
      "set": [
        "30-32",
        "22-25",
        "18-25"
      ]
    },
    {
      "id": "117",
      "data": "14-04-2026 21:15:00",
      "casa": "MULTIMEDIA MARCONI",
      "ospite": "KK FOREVER YOUNG",
      "giocata": true,
      "risultato": "1-2",
      "set": [
        "15-25",
        "18-25",
        "31-29"
      ]
    },
    {
      "id": "118",
      "data": "17-04-2026 21:00:00",
      "casa": "PINK PANTHERS DUEMILA12",
      "ospite": "DOPOLAVORO ATAC-COTRAL",
      "giocata": true,
      "risultato": "1-2",
      "set": [
        "23-25",
        "23-25",
        "25-23"
      ]
    },
    {
      "id": "119",
      "data": "13-04-2026 21:15:00",
      "casa": "ARVALIA MARCONI",
      "ospite": "KK LUPO ALBERTO",
      "giocata": true,
      "risultato": "2-1",
      "set": [
        "25-16",
        "29-27",
        "18-25"
      ]
    },
    {
      "id": "120",
      "data": "16-04-2026 20:45:00",
      "casa": "ASD TECNO-SPORT ORSI",
      "ospite": "KK THUNDER",
      "giocata": true,
      "risultato": "2-1",
      "set": [
        "25-19",
        "25-19",
        "22-25"
      ]
    },
    {
      "id": "121",
      "data": "14-04-2026 20:45:00",
      "casa": "KK PASTE",
      "ospite": "TODOLOCO",
      "giocata": true,
      "risultato": "2-1",
      "set": [
        "15-25",
        "25-22",
        "25-16"
      ]
    },
    {
      "id": "122",
      "data": "15-04-2026 21:00:00",
      "casa": "KK MAXSTERCLASS",
      "ospite": "CAM VOLLEY LIVE",
      "giocata": true,
      "risultato": "2-1",
      "set": [
        "22-25",
        "25-22",
        "25-21"
      ]
    },
    {
      "id": "123",
      "data": "23-04-2026 21:15:00",
      "casa": "DOPOLAVORO ATAC-COTRAL",
      "ospite": "MULTIMEDIA MARCONI",
      "giocata": true,
      "risultato": "1-2",
      "set": [
        "22-25",
        "25-15",
        "21-25"
      ]
    },
    {
      "id": "124",
      "data": "21-04-2026 21:00:00",
      "casa": "KK LUPO ALBERTO",
      "ospite": "ASD TECNO-SPORT ORSI",
      "giocata": true,
      "risultato": "1-2",
      "set": [
        "19-25",
        "25-17",
        "18-25"
      ]
    },
    {
      "id": "125",
      "data": "22-04-2026 21:00:00",
      "casa": "CAM VOLLEY LIVE",
      "ospite": "KK PASTE",
      "giocata": true,
      "risultato": "2-1",
      "set": [
        "25-23",
        "25-17",
        "22-25"
      ]
    },
    {
      "id": "126",
      "data": "22-04-2026 20:45:00",
      "casa": "KK THUNDER",
      "ospite": "ARVALIA MARCONI",
      "giocata": true,
      "risultato": "2-1",
      "set": [
        "29-27",
        "25-23",
        "17-25"
      ]
    },
    {
      "id": "127",
      "data": "23-04-2026 21:30:00",
      "casa": "KK FOREVER YOUNG",
      "ospite": "PINK PANTHERS DUEMILA12",
      "giocata": true,
      "risultato": "1-2",
      "set": [
        "21-25",
        "27-29",
        "25-23"
      ]
    },
    {
      "id": "128",
      "data": "23-04-2026 20:50:00",
      "casa": "TODOLOCO",
      "ospite": "KK MAXSTERCLASS",
      "giocata": true,
      "risultato": "1-2",
      "set": [
        "30-28",
        "22-25",
        "21-25"
      ]
    },
    {
      "id": "129",
      "data": "30-04-2026 21:15:00",
      "casa": "DOPOLAVORO ATAC-COTRAL",
      "ospite": "KK THUNDER",
      "giocata": true,
      "risultato": "0-3",
      "set": [
        "19-25",
        "23-25",
        "28-30"
      ]
    },
    {
      "id": "130",
      "data": "27-04-2026 21:15:00",
      "casa": "ARVALIA MARCONI",
      "ospite": "MULTIMEDIA MARCONI",
      "giocata": true,
      "risultato": "3-0",
      "set": [
        "25-16",
        "25-15",
        "25-21"
      ]
    },
    {
      "id": "131",
      "data": "30-04-2026 21:30:00",
      "casa": "KK FOREVER YOUNG",
      "ospite": "CAM VOLLEY LIVE",
      "giocata": true,
      "risultato": "1-2",
      "set": [
        "23-25",
        "25-17",
        "24-26"
      ]
    },
    {
      "id": "132",
      "data": "01-05-2026 21:00:00",
      "casa": "PINK PANTHERS DUEMILA12",
      "ospite": "KK PASTE",
      "giocata": true,
      "risultato": "2-1",
      "set": [
        "25-20",
        "25-16",
        "16-25"
      ]
    },
    {
      "id": "133",
      "data": "28-04-2026 20:45:00",
      "casa": "ASD TECNO-SPORT ORSI",
      "ospite": "TODOLOCO",
      "giocata": true,
      "risultato": "1-2",
      "set": [
        "25-16",
        "29-31",
        "18-25"
      ]
    },
    {
      "id": "134",
      "data": "27-04-2026 21:00:00",
      "casa": "KK MAXSTERCLASS",
      "ospite": "KK LUPO ALBERTO",
      "giocata": true,
      "risultato": "0-3",
      "set": [
        "23-25",
        "17-25",
        "23-25"
      ]
    },
    {
      "id": "135",
      "data": "05-05-2026 21:00:00",
      "casa": "KK LUPO ALBERTO",
      "ospite": "DOPOLAVORO ATAC-COTRAL",
      "giocata": true,
      "risultato": "1-2",
      "set": [
        "25-20",
        "24-26",
        "16-25"
      ]
    },
    {
      "id": "136",
      "data": "05-05-2026 21:15:00",
      "casa": "MULTIMEDIA MARCONI",
      "ospite": "ASD TECNO-SPORT ORSI",
      "giocata": true,
      "risultato": "1-2",
      "set": [
        "16-25",
        "25-22",
        "20-25"
      ]
    },
    {
      "id": "137",
      "data": "06-05-2026 21:00:00",
      "casa": "CAM VOLLEY LIVE",
      "ospite": "ARVALIA MARCONI",
      "giocata": true,
      "risultato": "2-1",
      "set": [
        "32-30",
        "25-20",
        "23-25"
      ]
    },
    {
      "id": "138",
      "data": "04-05-2026 20:45:00",
      "casa": "KK PASTE",
      "ospite": "KK THUNDER",
      "giocata": true,
      "risultato": "1-2",
      "set": [
        "25-15",
        "28-30",
        "19-25"
      ]
    },
    {
      "id": "139",
      "data": "07-05-2026 20:50:00",
      "casa": "TODOLOCO",
      "ospite": "KK FOREVER YOUNG",
      "giocata": true,
      "risultato": "1-2",
      "set": [
        "28-26",
        "29-31",
        "24-26"
      ]
    },
    {
      "id": "140",
      "data": "06-05-2026 21:00:00",
      "casa": "KK MAXSTERCLASS",
      "ospite": "PINK PANTHERS DUEMILA12",
      "giocata": true,
      "risultato": "1-2",
      "set": [
        "17-25",
        "22-25",
        "25-20"
      ]
    },
    {
      "id": "141",
      "data": "14-05-2026 21:15:00",
      "casa": "DOPOLAVORO ATAC-COTRAL",
      "ospite": "TODOLOCO",
      "giocata": true,
      "risultato": "1-2",
      "set": [
        "22-25",
        "25-20",
        "19-25"
      ]
    },
    {
      "id": "142",
      "data": "12-05-2026 21:15:00",
      "casa": "MULTIMEDIA MARCONI",
      "ospite": "KK MAXSTERCLASS",
      "giocata": true,
      "risultato": "2-1",
      "set": [
        "20-25",
        "25-22",
        "25-16"
      ]
    },
    {
      "id": "143",
      "data": "11-05-2026 21:15:00",
      "casa": "ARVALIA MARCONI",
      "ospite": "PINK PANTHERS DUEMILA12",
      "giocata": true,
      "risultato": "2-1",
      "set": [
        "19-25",
        "28-26",
        "29-27"
      ]
    },
    {
      "id": "144",
      "data": "13-05-2026 20:45:00",
      "casa": "KK THUNDER",
      "ospite": "KK FOREVER YOUNG",
      "giocata": true,
      "risultato": "1-2",
      "set": [
        "22-25",
        "28-26",
        "17-25"
      ]
    },
    {
      "id": "145",
      "data": "12-05-2026 20:45:00",
      "casa": "ASD TECNO-SPORT ORSI",
      "ospite": "CAM VOLLEY LIVE",
      "giocata": true,
      "risultato": "2-1",
      "set": [
        "20-25",
        "25-16",
        "25-19"
      ]
    },
    {
      "id": "146",
      "data": "12-05-2026 21:00:00",
      "casa": "KK LUPO ALBERTO",
      "ospite": "KK PASTE",
      "giocata": true,
      "risultato": "1-2",
      "set": [
        "23-25",
        "29-27",
        "16-25"
      ]
    },
    {
      "id": "147",
      "data": "30-03-2026 21:25:00",
      "casa": "KK 30TMCAP",
      "ospite": "ALPI STARTER",
      "giocata": true,
      "risultato": "3-0",
      "set": [
        "29-27",
        "31-29",
        "25-23"
      ]
    },
    {
      "id": "148",
      "data": "31-03-2026 21:30:00",
      "casa": "KK ASTRAVOLLEY",
      "ospite": "SHARKS ASD",
      "giocata": true,
      "risultato": "3-0",
      "set": [
        "25-16",
        "25-18",
        "25-15"
      ]
    },
    {
      "id": "149",
      "data": "31-03-2026 21:00:00",
      "casa": "SANTA MONICA",
      "ospite": "ASD TECNO-SPORT PINGUINI",
      "giocata": true,
      "risultato": "1-2",
      "set": [
        "19-25",
        "23-25",
        "25-19"
      ]
    },
    {
      "id": "150",
      "data": "03-04-2026 20:45:00",
      "casa": "NEW PICCHE",
      "ospite": "ROMA SPORTS",
      "giocata": true,
      "risultato": "2-1",
      "set": [
        "15-25",
        "25-23",
        "25-23"
      ]
    },
    {
      "id": "151",
      "data": "31-03-2026 21:00:00",
      "casa": "BEAT",
      "ospite": "ASD SFERA ROSSA",
      "giocata": true,
      "risultato": "2-1",
      "set": [
        "25-17",
        "20-25",
        "25-20"
      ]
    },
    {
      "id": "153",
      "data": "17-04-2026 21:15:00",
      "casa": "ALPI STARTER",
      "ospite": "SHARKS ASD",
      "giocata": true,
      "risultato": "3-0",
      "set": [
        "28-26",
        "25-15",
        "25-16"
      ]
    },
    {
      "id": "154",
      "data": "17-04-2026 21:30:00",
      "casa": "ASD SFERA ROSSA",
      "ospite": "NEW PICCHE",
      "giocata": true,
      "risultato": "1-2",
      "set": [
        "22-25",
        "25-16",
        "23-25"
      ]
    },
    {
      "id": "155",
      "data": "14-04-2026 21:00:00",
      "casa": "BEAT",
      "ospite": "SANTA MONICA",
      "giocata": true,
      "risultato": "0-3",
      "set": [
        "28-30",
        "24-26",
        "29-31"
      ]
    },
    {
      "id": "156",
      "data": "14-04-2026 21:00:00",
      "casa": "ASD TECNO-SPORT PINGUINI",
      "ospite": "KK ASTRAVOLLEY",
      "giocata": true,
      "risultato": "2-1",
      "set": [
        "23-25",
        "25-15",
        "25-19"
      ]
    },
    {
      "id": "157",
      "data": "17-04-2026 21:00:00",
      "casa": "ROMA SPORTS",
      "ospite": "KK 30TMCAP",
      "giocata": true,
      "risultato": "2-1",
      "set": [
        "25-17",
        "30-28",
        "21-25"
      ]
    },
    {
      "id": "159",
      "data": "24-04-2026 21:15:00",
      "casa": "ALPI STARTER",
      "ospite": "ASD TECNO-SPORT PINGUINI",
      "giocata": true,
      "risultato": "2-1",
      "set": [
        "30-28",
        "22-25",
        "25-23"
      ]
    },
    {
      "id": "160",
      "data": "22-04-2026 21:30:00",
      "casa": "SHARKS ASD",
      "ospite": "ROMA SPORTS",
      "giocata": true,
      "risultato": "1-2",
      "set": [
        "21-25",
        "25-20",
        "15-25"
      ]
    },
    {
      "id": "161",
      "data": "20-04-2026 21:25:00",
      "casa": "KK 30TMCAP",
      "ospite": "ASD SFERA ROSSA",
      "giocata": true,
      "risultato": "2-1",
      "set": [
        "16-25",
        "29-27",
        "25-16"
      ]
    },
    {
      "id": "162",
      "data": "21-04-2026 21:30:00",
      "casa": "KK ASTRAVOLLEY",
      "ospite": "BEAT",
      "giocata": true,
      "risultato": "1-2",
      "set": [
        "28-30",
        "19-25",
        "25-18"
      ]
    },
    {
      "id": "165",
      "data": "28-04-2026 21:00:00",
      "casa": "BEAT",
      "ospite": "ALPI STARTER",
      "giocata": true,
      "risultato": "1-2",
      "set": [
        "27-29",
        "25-18",
        "23-25"
      ]
    },
    {
      "id": "166",
      "data": "01-05-2026 21:30:00",
      "casa": "ASD SFERA ROSSA",
      "ospite": "SHARKS ASD",
      "giocata": true,
      "risultato": "1-2",
      "set": [
        "17-25",
        "25-21",
        "19-25"
      ]
    },
    {
      "id": "167",
      "data": "28-04-2026 21:00:00",
      "casa": "SANTA MONICA",
      "ospite": "KK 30TMCAP",
      "giocata": true,
      "risultato": "1-2",
      "set": [
        "23-25",
        "25-18",
        "19-25"
      ]
    },
    {
      "id": "168",
      "data": "01-05-2026 20:45:00",
      "casa": "NEW PICCHE",
      "ospite": "KK ASTRAVOLLEY",
      "giocata": true,
      "risultato": "0-3",
      "set": [
        "21-25",
        "21-25",
        "18-25"
      ]
    },
    {
      "id": "169",
      "data": "01-05-2026 21:00:00",
      "casa": "ROMA SPORTS",
      "ospite": "ASD TECNO-SPORT PINGUINI",
      "giocata": true,
      "risultato": "2-1",
      "set": [
        "25-16",
        "21-25",
        "25-16"
      ]
    },
    {
      "id": "171",
      "data": "06-05-2026 21:30:00",
      "casa": "SHARKS ASD",
      "ospite": "SANTA MONICA",
      "giocata": true,
      "risultato": "1-2",
      "set": [
        "25-23",
        "22-25",
        "18-25"
      ]
    },
    {
      "id": "172",
      "data": "08-05-2026 21:15:00",
      "casa": "ALPI STARTER",
      "ospite": "NEW PICCHE",
      "giocata": true,
      "risultato": "2-1",
      "set": [
        "21-25",
        "25-15",
        "25-20"
      ]
    },
    {
      "id": "173",
      "data": "05-05-2026 21:00:00",
      "casa": "ASD TECNO-SPORT PINGUINI",
      "ospite": "ASD SFERA ROSSA",
      "giocata": true,
      "risultato": "1-2",
      "set": [
        "18-25",
        "25-16",
        "22-25"
      ]
    },
    {
      "id": "174",
      "data": "08-05-2026 21:00:00",
      "casa": "ROMA SPORTS",
      "ospite": "BEAT",
      "giocata": true,
      "risultato": "0-3",
      "set": [
        "15-25",
        "19-25",
        "22-25"
      ]
    },
    {
      "id": "175",
      "data": "04-05-2026 21:25:00",
      "casa": "KK 30TMCAP",
      "ospite": "KK ASTRAVOLLEY",
      "giocata": true,
      "risultato": "0-3",
      "set": [
        "22-25",
        "16-25",
        "16-25"
      ]
    }
  ]
}